rehn/__init__.py
rehn/main.py
rehn/utils/__init__.py
rehn/utils/pc2raster.py
rehn/utils/ply.py
ReHN-1.0.2.dist-info/LICENSE
ReHN-1.0.2.dist-info/METADATA
ReHN-1.0.2.dist-info/WHEEL
ReHN-1.0.2.dist-info/entry_points.txt
ReHN-1.0.2.dist-info/top_level.txt
ReHN-1.0.2.dist-info/RECORD
