Metadata-Version: 2.1
Name: ReHN
Version: 1.0.2
Summary: Height normalization for point clouds using the Re-Height Normalization (ReHN) algorithm.
Author-email: Liwei Deng <dlw3d@qq.com>
License:                                  Apache License
Project-URL: Repository, https://github.com/DLW3D/ReHN.git
Project-URL: Issues, https://github.com/DLW3D/ReHN/issues
Keywords: Height normalization,point clouds,LiDAR,3D,ReHN
Classifier: Development Status :: 4 - Beta
Classifier: Intended Audience :: Science/Research
Classifier: Topic :: Scientific/Engineering :: GIS
Classifier: License :: OSI Approved :: Apache Software License
Classifier: Programming Language :: Python :: 3
Requires-Python: >=3.6.0
License-File: LICENSE
Requires-Dist: numpy
Requires-Dist: pykdtree
Provides-Extra: csf
Requires-Dist: cloth-simulation-filter; extra == "csf"
Requires-Dist: numpy<2; extra == "csf"
